class_based_fastapi/__init__.py
class_based_fastapi/decorators.py
class_based_fastapi/defaults.py
class_based_fastapi/routable.py
class_based_fastapi/route_args.py
class_based_fastapi/templates_formatting.py
class_based_fastapi/utilities.py
class_based_fastapi-1.1.0.dist-info/LICENSE
class_based_fastapi-1.1.0.dist-info/METADATA
class_based_fastapi-1.1.0.dist-info/WHEEL
class_based_fastapi-1.1.0.dist-info/top_level.txt
class_based_fastapi-1.1.0.dist-info/RECORD
