Metadata-Version: 2.2
Name: class-based-fastapi
Version: 1.1.0
Summary: Class based routing for FastAPI
Home-page: https://github.com/XDeepZeroX/class-based-fastapi
Author: XDeepZeroX
License: MIT
Keywords: FastAPI,Class,Instance,Routing
Platform: all
Classifier: Development Status :: 5 - Production/Stable
Classifier: Intended Audience :: Developers
Classifier: License :: OSI Approved :: MIT License
Classifier: Framework :: FastAPI
Classifier: Framework :: AsyncIO
Classifier: Operating System :: OS Independent
Classifier: Programming Language :: Python
Classifier: Programming Language :: Python :: 3.8
Classifier: Programming Language :: Python :: 3.9
Classifier: Programming Language :: Python :: 3.10
Classifier: Programming Language :: Python :: 3 :: Only
Classifier: Topic :: Internet :: WWW/HTTP
Classifier: Topic :: Internet :: WWW/HTTP :: Session
Classifier: Typing :: Typed
Requires-Python: >=3.8, <4
License-File: LICENSE
Requires-Dist: fastapi>=0.115.6
Requires-Dist: pydantic>=2.10.5
Provides-Extra: dev
Requires-Dist: requests>=2.32.3; extra == "dev"
Requires-Dist: uvicorn>=0.34.0; extra == "dev"
Requires-Dist: pep8-naming==0.13.1; extra == "dev"
Requires-Dist: flake8==4.0.1; extra == "dev"
Requires-Dist: flake8-annotations==2.9.1; extra == "dev"
Requires-Dist: flake8-annotations-coverage==0.0.6; extra == "dev"
Requires-Dist: flake8-bugbear==22.7.1; extra == "dev"
Requires-Dist: flake8-builtins==1.5.3; extra == "dev"
Requires-Dist: flake8-class-attributes-order==0.1.3; extra == "dev"
Requires-Dist: flake8-cognitive-complexity==0.1.0; extra == "dev"
Requires-Dist: flake8-commas==2.1.0; extra == "dev"
Requires-Dist: flake8-comprehensions==3.10.0; extra == "dev"
Requires-Dist: flake8-docstrings==1.6.0; extra == "dev"
Requires-Dist: flake8-encodings==0.5.0.post1; extra == "dev"
Requires-Dist: flake8-expression-complexity==0.0.11; extra == "dev"
Requires-Dist: flake8-fastapi==0.7.0; extra == "dev"
Requires-Dist: flake8-helper==0.2.1; extra == "dev"
Requires-Dist: flake8-import-order==0.18.1; extra == "dev"
Requires-Dist: flake8-multiline-containers==0.0.19; extra == "dev"
Requires-Dist: flake8-newspaper-style==0.3.0; extra == "dev"
Requires-Dist: flake8-pie==0.15.0; extra == "dev"
Requires-Dist: flake8-plugin-utils==1.3.2; extra == "dev"
Requires-Dist: flake8-polyfill==1.0.2; extra == "dev"
Requires-Dist: flake8-quotes==3.3.1; extra == "dev"
Requires-Dist: flake8-return==1.1.3; extra == "dev"
Requires-Dist: flake8-scream==0.1.0; extra == "dev"
Requires-Dist: flake8-simplify==0.19.3; extra == "dev"
Requires-Dist: flake8-unused-arguments==0.0.11; extra == "dev"
Requires-Dist: flake8-useless-assert==0.4.3; extra == "dev"
Requires-Dist: flake8-variables-names==0.0.5; extra == "dev"
Provides-Extra: docs
Requires-Dist: mkdocs-material>=8.4.3; extra == "docs"
Requires-Dist: pygments>=2.13.0; extra == "docs"
Requires-Dist: mkdocs-glightbox>=0.2.1; extra == "docs"
Requires-Dist: markdown-include>=0.7.0; extra == "docs"
Provides-Extra: test
Requires-Dist: pytest>=6.2.5; extra == "test"
Requires-Dist: requests>=2.28.1; extra == "test"
Requires-Dist: sqlmodel>=0.0.22; extra == "test"
Requires-Dist: httpx>=0.28.1; extra == "test"
Provides-Extra: all
Requires-Dist: fastapi>=0.115.6; extra == "all"
Requires-Dist: pydantic>=2.10.5; extra == "all"
Requires-Dist: requests>=2.32.3; extra == "all"
Requires-Dist: uvicorn>=0.34.0; extra == "all"
Requires-Dist: pep8-naming==0.13.1; extra == "all"
Requires-Dist: flake8==4.0.1; extra == "all"
Requires-Dist: flake8-annotations==2.9.1; extra == "all"
Requires-Dist: flake8-annotations-coverage==0.0.6; extra == "all"
Requires-Dist: flake8-bugbear==22.7.1; extra == "all"
Requires-Dist: flake8-builtins==1.5.3; extra == "all"
Requires-Dist: flake8-class-attributes-order==0.1.3; extra == "all"
Requires-Dist: flake8-cognitive-complexity==0.1.0; extra == "all"
Requires-Dist: flake8-commas==2.1.0; extra == "all"
Requires-Dist: flake8-comprehensions==3.10.0; extra == "all"
Requires-Dist: flake8-docstrings==1.6.0; extra == "all"
Requires-Dist: flake8-encodings==0.5.0.post1; extra == "all"
Requires-Dist: flake8-expression-complexity==0.0.11; extra == "all"
Requires-Dist: flake8-fastapi==0.7.0; extra == "all"
Requires-Dist: flake8-helper==0.2.1; extra == "all"
Requires-Dist: flake8-import-order==0.18.1; extra == "all"
Requires-Dist: flake8-multiline-containers==0.0.19; extra == "all"
Requires-Dist: flake8-newspaper-style==0.3.0; extra == "all"
Requires-Dist: flake8-pie==0.15.0; extra == "all"
Requires-Dist: flake8-plugin-utils==1.3.2; extra == "all"
Requires-Dist: flake8-polyfill==1.0.2; extra == "all"
Requires-Dist: flake8-quotes==3.3.1; extra == "all"
Requires-Dist: flake8-return==1.1.3; extra == "all"
Requires-Dist: flake8-scream==0.1.0; extra == "all"
Requires-Dist: flake8-simplify==0.19.3; extra == "all"
Requires-Dist: flake8-unused-arguments==0.0.11; extra == "all"
Requires-Dist: flake8-useless-assert==0.4.3; extra == "all"
Requires-Dist: flake8-variables-names==0.0.5; extra == "all"
Requires-Dist: mkdocs-material>=8.4.3; extra == "all"
Requires-Dist: pygments>=2.13.0; extra == "all"
Requires-Dist: mkdocs-glightbox>=0.2.1; extra == "all"
Requires-Dist: markdown-include>=0.7.0; extra == "all"
Requires-Dist: pytest>=6.2.5; extra == "all"
Requires-Dist: requests>=2.28.1; extra == "all"
Requires-Dist: sqlmodel>=0.0.22; extra == "all"
Requires-Dist: httpx>=0.28.1; extra == "all"
Dynamic: author
Dynamic: classifier
Dynamic: description
Dynamic: description-content-type
Dynamic: home-page
Dynamic: keywords
Dynamic: license
Dynamic: platform
Dynamic: provides-extra
Dynamic: requires-dist
Dynamic: requires-python
Dynamic: summary
